ael_satellite_tools/__init__.py
ael_satellite_tools/satellite_general.py
ael_satellite_tools/satellite_plotting.py
ael_satellite_tools/plotting/Himawari.py
ael_satellite_tools/plotting/__init__.py
ael_satellite_tools/preprocess/CloudSat.py
ael_satellite_tools/preprocess/Himawari.py
ael_satellite_tools/preprocess/RO.py
ael_satellite_tools/preprocess/__init__.py
ael_satellite_tools/preprocess/himawari_LUT/ext.01.H08
ael_satellite_tools/preprocess/himawari_LUT/ext.01.H09
ael_satellite_tools/preprocess/himawari_LUT/sir.01.H08
ael_satellite_tools/preprocess/himawari_LUT/sir.01.H09
ael_satellite_tools/preprocess/himawari_LUT/sir.02.H08
ael_satellite_tools/preprocess/himawari_LUT/sir.02.H09
ael_satellite_tools/preprocess/himawari_LUT/tir.01.H08
ael_satellite_tools/preprocess/himawari_LUT/tir.01.H09
ael_satellite_tools/preprocess/himawari_LUT/tir.02.H08
ael_satellite_tools/preprocess/himawari_LUT/tir.02.H09
ael_satellite_tools/preprocess/himawari_LUT/tir.03.H08
ael_satellite_tools/preprocess/himawari_LUT/tir.03.H09
ael_satellite_tools/preprocess/himawari_LUT/tir.04.H08
ael_satellite_tools/preprocess/himawari_LUT/tir.04.H09
ael_satellite_tools/preprocess/himawari_LUT/tir.05.H08
ael_satellite_tools/preprocess/himawari_LUT/tir.05.H09
ael_satellite_tools/preprocess/himawari_LUT/tir.06.H08
ael_satellite_tools/preprocess/himawari_LUT/tir.06.H09
ael_satellite_tools/preprocess/himawari_LUT/tir.07.H08
ael_satellite_tools/preprocess/himawari_LUT/tir.07.H09
ael_satellite_tools/preprocess/himawari_LUT/tir.08.H08
ael_satellite_tools/preprocess/himawari_LUT/tir.08.H09
ael_satellite_tools/preprocess/himawari_LUT/tir.09.H08
ael_satellite_tools/preprocess/himawari_LUT/tir.09.H09
ael_satellite_tools/preprocess/himawari_LUT/tir.10.H08
ael_satellite_tools/preprocess/himawari_LUT/tir.10.H09
ael_satellite_tools/preprocess/himawari_LUT/vis.01.H08
ael_satellite_tools/preprocess/himawari_LUT/vis.01.H09
ael_satellite_tools/preprocess/himawari_LUT/vis.02.H08
ael_satellite_tools-0.0.13.dist-info/METADATA
ael_satellite_tools-0.0.13.dist-info/WHEEL
ael_satellite_tools-0.0.13.dist-info/top_level.txt
ael_satellite_tools-0.0.13.dist-info/RECORD
